transition_detect/__init__.py
transition_detect/config.yaml
transition_detect/main.py
transition_detect/models/transnetv2-pytorch-weights.pth
transition_detect/transnetv2/__init__.py
transition_detect/transnetv2/main.py
transition_detect/transnetv2/network.py
transition_detect/transnetv2/typings.py
transition_detect/utils/__init__.py
transition_detect/utils/config.py
transition_detect/utils/download_file.py
transition_detect/utils/logger.py
transition_detect/utils/utils.py
transition_detect-0.1.0.dist-info/licenses/LICENSE
transition_detect-0.1.0.dist-info/METADATA
transition_detect-0.1.0.dist-info/WHEEL
transition_detect-0.1.0.dist-info/entry_points.txt
transition_detect-0.1.0.dist-info/top_level.txt
transition_detect-0.1.0.dist-info/RECORD
