Metadata-Version: 2.4
Name: transition_detect
Version: 0.1.0
Summary: Video Transition Detection and Segmentation
Home-page: https://github.com/SWHL/TransitionDetect
Author: SWHL
Author-email: liekkaskono@163.com
License: Apache-2.0
Keywords: transition_detect,transnetv2
Platform: Any
Classifier: Programming Language :: Python :: 3.6
Classifier: Programming Language :: Python :: 3.7
Classifier: Programming Language :: Python :: 3.8
Classifier: Programming Language :: Python :: 3.9
Classifier: Programming Language :: Python :: 3.10
Classifier: Programming Language :: Python :: 3.11
Classifier: Programming Language :: Python :: 3.12
Classifier: Programming Language :: Python :: 3.13
Classifier: Programming Language :: Python :: 3.14
Requires-Python: >=3.6,<4
License-File: LICENSE
Requires-Dist: ffmpeg-python
Requires-Dist: colorlog
Requires-Dist: requests
Requires-Dist: torch
Requires-Dist: PyYAML
Requires-Dist: numpy
Requires-Dist: tqdm
Dynamic: author
Dynamic: author-email
Dynamic: classifier
Dynamic: description
Dynamic: description-content-type
Dynamic: home-page
Dynamic: keywords
Dynamic: license
Dynamic: license-file
Dynamic: platform
Dynamic: requires-dist
Dynamic: requires-python
Dynamic: summary
